Metadata-Version: 2.1
Name: fn-2187-distributions
Version: 0.1
Summary: Gaussian distributions
Home-page: UNKNOWN
Author: Adesugba Oluwatoba
Author-email: tobaadesugba@gmail.com
License: UNKNOWN
Platform: UNKNOWN
